<?xml version="1.0" encoding="UTF-8"?>
<index>
	<title>Source of NelsonApr09</title>
	<nodes>
		<node label="html-template">
			<node label="history">
				<node label="history.css" icon="cssIcon" url="source/html-template/history/history.css.html"/>
				<node label="history.js" url="source/html-template/history/history.js.txt"/>
				<node label="historyFrame.html" icon="htmlIcon" url="source/html-template/history/historyFrame.html"/>
			</node>
			<node label="AC_OETags.js" url="source/html-template/AC_OETags.js.txt"/>
			<node label="index.template.html" icon="htmlIcon" url="source/html-template/index.template.html"/>
			<node label="playerProductInstall.swf" icon="swfIcon" url="source/html-template/playerProductInstall.swf"/>
		</node>
		<node label="libs">
		</node>
		<node label="src" icon="classpathIcon" expanded="true">
			<node label="com" icon="packageIcon" expanded="true">
				<node label="CImage.as" icon="actionScriptIcon" url="source/com/CImage.as.html"/>
				<node label="RotateEffect.as" icon="actionScriptIcon" url="source/com/RotateEffect.as.html"/>
				<node label="RotateTweenInstance.as" icon="actionScriptIcon" url="source/com/RotateTweenInstance.as.html"/>
			</node>
			<node label="services" icon="packageIcon" expanded="true">
				<node label="PhotoService.mxml" icon="mxmlIcon" url="source/services/PhotoService.mxml.html"/>
			</node>
			<node selected="true" label="NelsonApr09.mxml" icon="mxmlAppIcon" url="source/NelsonApr09.mxml.html"/>
		</node>
	</nodes>
</index>
